repo_architecture_mcp/__init__.py
repo_architecture_mcp/architecture_analyzer.py
repo_architecture_mcp/cache_manager.py
repo_architecture_mcp/config.py
repo_architecture_mcp/diagram_generator.py
repo_architecture_mcp/errors.py
repo_architecture_mcp/logging_config.py
repo_architecture_mcp/main.py
repo_architecture_mcp/memory_manager.py
repo_architecture_mcp/models.py
repo_architecture_mcp/parallel_processor.py
repo_architecture_mcp/performance_optimizer.py
repo_architecture_mcp/repository_manager.py
repo_architecture_mcp/server.py
repo_architecture_mcp/parsers/__init__.py
repo_architecture_mcp/parsers/base.py
repo_architecture_mcp/parsers/java_parser.py
repo_architecture_mcp/parsers/javascript_parser.py
repo_architecture_mcp/parsers/python_parser.py
repo_architecture_mcp/parsers/typescript_parser.py
repo_architecture_mcp_server-0.1.1.dist-info/licenses/LICENSE
repo_architecture_mcp_server-0.1.1.dist-info/METADATA
repo_architecture_mcp_server-0.1.1.dist-info/WHEEL
repo_architecture_mcp_server-0.1.1.dist-info/entry_points.txt
repo_architecture_mcp_server-0.1.1.dist-info/top_level.txt
repo_architecture_mcp_server-0.1.1.dist-info/RECORD
