Metadata-Version: 2.4
Name: repo-architecture-mcp-server
Version: 0.1.1
Summary: MCP server for analyzing GitHub repositories and generating architectural diagrams
Author-email: Vinit Kumar <k.vinit2020@gmail.com>
Classifier: Development Status :: 3 - Alpha
Classifier: Intended Audience :: Developers
Classifier: License :: OSI Approved :: MIT License
Classifier: Programming Language :: Python :: 3
Classifier: Programming Language :: Python :: 3.10
Classifier: Programming Language :: Python :: 3.11
Classifier: Programming Language :: Python :: 3.12
Requires-Python: >=3.10
License-File: LICENSE
Requires-Dist: mcp>=1.0.0
Requires-Dist: aiohttp>=3.8.0
Requires-Dist: GitPython>=3.1.0
Requires-Dist: networkx>=3.0
Requires-Dist: pydantic>=2.0.0
Requires-Dist: asyncio-mqtt>=0.11.0
Requires-Dist: PyYAML>=6.0.0
Provides-Extra: dev
Requires-Dist: pytest>=7.0.0; extra == "dev"
Requires-Dist: pytest-asyncio>=0.21.0; extra == "dev"
Requires-Dist: black>=23.0.0; extra == "dev"
Requires-Dist: mypy>=1.0.0; extra == "dev"
Requires-Dist: pre-commit>=3.0.0; extra == "dev"
Requires-Dist: coverage>=7.0.0; extra == "dev"
Provides-Extra: performance
Requires-Dist: psutil>=5.9.0; extra == "performance"
Dynamic: license-file
